setup.cfg
setup.py
docgo/__init__.py
docgo/run.py
docgo.egg-info/PKG-INFO
docgo.egg-info/SOURCES.txt
docgo.egg-info/dependency_links.txt
docgo.egg-info/top_level.txt