Metadata-Version: 1.1
Name: docgo
Version: 0.3
Summary: This docgo provides a pydoc's tradutor for pt-br
Home-page: https://github.com/horacioibrahim/docgo
Author: Horacio Ibrahim
Author-email: horacioibrahim@gmail.com
License: MIT License
Download-URL: https://github.com/horacioibrahim/docgo/releases/tag/0.3
Keywords: docgo,translate,pydoc
Platform: UNKNOWN
Classifier: Development Status :: 5 - Production/Stable
Classifier: Intended Audience :: Education
Classifier: Natural Language :: Portuguese (Brazilian)
Classifier: Operating System :: OS Independent
Classifier: Programming Language :: Python
Classifier: Programming Language :: Python :: 2
Classifier: Programming Language :: Python :: 2.6
Classifier: Programming Language :: Python :: 2.7
Classifier: Topic :: Software Development :: Libraries :: Python Modules
